LICENSE
MANIFEST.in
README.markdown
setup.py
colorful/__init__.py
colorful/fields.py
colorful/widgets.py
colorful/static/colorful/arrow.gif
colorful/static/colorful/colorPicker.css
colorful/static/colorful/jQuery.colorPicker.js
colorful/static/colorful/jquery.colorPicker.min.js
twentytab_colorful.egg-info/PKG-INFO
twentytab_colorful.egg-info/SOURCES.txt
twentytab_colorful.egg-info/dependency_links.txt
twentytab_colorful.egg-info/not-zip-safe
twentytab_colorful.egg-info/top_level.txt