Metadata-Version: 1.1
Name: twentytab-colorful
Version: 0.1
Summary: An extension to the Django web framework that provides database and form color fields
Home-page: https://github.com/20tab/twentytab-colorful
Author: Simon Charette
Author-email: charette.s@gmail.com
License: MIT License
Platform: UNKNOWN
Classifier: Development Status :: 1 - Planning
Classifier: Environment :: Web Environment
Classifier: Framework :: Django
Classifier: Intended Audience :: Developers
Classifier: License :: OSI Approved :: MIT License
Classifier: Operating System :: OS Independent
Classifier: Programming Language :: Python
Classifier: Topic :: Software Development :: Libraries :: Python Modules
Requires: Django (>=1.6)
